Metadata-Version: 2.2
Name: Stremio
Version: 0.1.0.dev0
Summary: An asynchronous Python library for building Stremio addons with ease
Home-page: https://github.com/AYMENJD/stremio
Author: AYMEN Mohammed
Author-email: let.me.code.safe@gmail.com
License: MIT
Project-URL: Source, https://github.com/AYMENJD/stremio
Project-URL: Tracker, https://github.com/AYMENJD/stremio/issues
Keywords: stremio,stremio-addon,stremio-addon-sdk,addon,plugin,async
Requires-Python: >=3.9
License-File: LICENSE
Requires-Dist: blacksheep
Requires-Dist: uvicorn
Requires-Dist: packaging
Dynamic: author
Dynamic: author-email
Dynamic: description
Dynamic: description-content-type
Dynamic: home-page
Dynamic: keywords
Dynamic: license
Dynamic: project-url
Dynamic: requires-dist
Dynamic: requires-python
Dynamic: summary
